file2tree/__init__.py
file2tree/file2tree.py
file2tree-0.0.1.dist-info/METADATA
file2tree-0.0.1.dist-info/WHEEL
file2tree-0.0.1.dist-info/entry_points.txt
file2tree-0.0.1.dist-info/top_level.txt
file2tree-0.0.1.dist-info/RECORD
