Metadata-Version: 2.1
Name: file2tree
Version: 0.0.1
Summary: file2tree
Home-page: https://github.com/guofei9987/file2tree
Author: Guo Fei
Author-email: guofei9987@foxmail.com
License: MIT
Platform: UNKNOWN
